hj_proj_module/__init__.py
hj_proj_module/logging/__init__.py
hj_proj_module/logging/log_utils.py
hj_proj_module/my_function.py
hj_proj_module/stock_alarm/__init__.py
hj_proj_module/stock_alarm/models.py
hj_proj_module/stock_alarm/pubsub_client.py
hj_proj_module/utils/common.py
hj_proj_module-0.1.36.dist-info/METADATA
hj_proj_module-0.1.36.dist-info/WHEEL
hj_proj_module-0.1.36.dist-info/RECORD
