Metadata-Version: 2.1
Name: hj-proj-module
Version: 0.1.36
Summary: Packages for HJ Projects
Home-page: https://github.com/hj12121/hj-proj-module
License: MIT
Keywords: HJ
Author: Hojung Yun
Author-email: hojung.yun@gmail.com
Requires-Python: >=3.11,<4.0
Classifier: Environment :: Console
Classifier: License :: OSI Approved :: MIT License
Classifier: Operating System :: OS Independent
Classifier: Programming Language :: Python :: 3
Classifier: Programming Language :: Python :: 3.11
Classifier: Programming Language :: Python :: 3.12
Classifier: Topic :: Software Development :: Documentation
Classifier: Topic :: Software Development :: Libraries :: Python Modules
Requires-Dist: google-cloud-pubsub (>=2.21.1,<3.0.0)
Requires-Dist: orjson (>=3.10.1,<4.0.0)
Requires-Dist: python-json-logger (>=2.0.7,<3.0.0)
Requires-Dist: pytz (>=2024.1,<2025.0)
Requires-Dist: tzlocal (>=5.2,<6.0)
Project-URL: Repository, https://github.com/hj12121/hj-proj-module
